[1,["c4QsPL0KlIjLO6UrE5JTNg","e2oWcFENdJua11QdL7XT5G","cexvZBzxRF8qmVO3nDsBY3","7afD+c51hCqbnPRSO0/vz7","213bUms8lIHYiTZKcPrlLl","30n+wbjptLc4Uv/T4YaPhg","90HGjCx1lKsbirxdwgSS5J","18OeV6oVtDaZwTWkcrhcXs","90ZkBFLxVI7JAk3oDnP9R2","410HhsMuRDgKzTLu3rD0Cq","a9D059wfJL+rMnMtr0Bccx","cbe4D9iqhFlrtwGyUjsSWX","c0Ga1HKeJNQ5PeQ7tyo8Sv","8dWmIUgEJMjLdH5A3Crt6S","664BiMo6VIpYybRG1VgTy9","60VgUqcTlAppyTF+tswaEF"],["value","_textureSetter"],["cc.SpriteFrame",["cc.AnimationClip",["_name","_duration","sample","wrapMode","events","curveData"],-2,11]],[[1,0,1,2,3,4,5,6]],[[[{"name":"loading2","rect":[175,152,183,179],"offset":[-15.5,-19],"originalSize":[564,445],"capInsets":[0,0,0,0]}],[0],0,[0],[1],[1]],[[{"name":"loading8","rect":[147,136,217,195],"offset":[-26.5,-11],"originalSize":[564,445],"capInsets":[0,0,0,0]}],[0],0,[0],[1],[2]],[[{"name":"loading7","rect":[212,148,174,181],"offset":[17,-16],"originalSize":[564,445],"capInsets":[0,0,0,0]}],[0],0,[0],[1],[3]],[[{"name":"loading6","rect":[225,152,182,178],"offset":[34,-18.5],"originalSize":[564,445],"capInsets":[0,0,0,0]}],[0],0,[0],[1],[4]],[[{"name":"loading3","rect":[196,149,174,181],"offset":[1,-17],"originalSize":[564,445],"capInsets":[0,0,0,0]}],[0],0,[0],[1],[5]],[[{"name":"loading5","rect":[230,131,193,199],"offset":[44.5,-8],"originalSize":[564,445],"capInsets":[0,0,0,0]}],[0],0,[0],[1],[6]],[[{"name":"loading1","rect":[159,132,193,199],"offset":[-26.5,-9],"originalSize":[564,445],"capInsets":[0,0,0,0]}],[0],0,[0],[1],[7]],[[{"name":"loading4","rect":[218,136,211,194],"offset":[41.5,-10.5],"originalSize":[564,445],"capInsets":[0,0,0,0]}],[0],0,[0],[1],[8]],[[[0,"loading_gif",0.6101694915254238,59,2,[{"frame":0,"func":"","params":[]}],[{},"comps",11,[{},"cc.Sprite",11,[{},"spriteFrame",12,[[[{"frame":0.01694915254237288},"value",6,0],[{"frame":0.0847457627118644},"value",6,1],[{"frame":0.1694915254237288},"value",6,2],[{"frame":0.2542372881355932},"value",6,3],[{"frame":0.3389830508474576},"value",6,4],[{"frame":0.423728813559322},"value",6,5],[{"frame":0.5084745762711864},"value",6,6],[{"frame":0.576271186440678},"value",6,7],[{"frame":0.5932203389830508},"value",6,8]],11,11,11,11,11,11,11,11,11]]]]]],0,0,[0,0,0,0,0,0,0,0,0],[0,0,0,0,0,0,0,0,0],[0,9,10,11,12,13,14,0,15]]]]